<?xml version="1.0" encoding="UTF-8"?>
<DEFECTS>
  <DEFECT>
    <SFA>
      <FILEPATH>c:\vsdev\classes\gameengines\insightengine\directx11renderingengine\graphics</FILEPATH>
      <FILENAME>vertex.h</FILENAME>
      <LINE>6</LINE>
      <COLUMN>1</COLUMN>
    </SFA>
    <DEFECTCODE>26495</DEFECTCODE>
    <DESCRIPTION>Variable 'Vertex2D::pos' is uninitialized. Always initialize a member variable (type.6).</DESCRIPTION>
    <FUNCTION>Vertex2D::{ctor}</FUNCTION>
    <DECORATED>??0Vertex2D@@QEAA@XZ</DECORATED>
    <FUNCLINE>6</FUNCLINE>
    <PATH></PATH>
  </DEFECT>
  <DEFECT>
    <SFA>
      <FILEPATH>c:\vsdev\classes\gameengines\insightengine\directx11renderingengine\graphics</FILEPATH>
      <FILENAME>vertex.h</FILENAME>
      <LINE>6</LINE>
      <COLUMN>1</COLUMN>
    </SFA>
    <DEFECTCODE>26495</DEFECTCODE>
    <DESCRIPTION>Variable 'Vertex2D::normal' is uninitialized. Always initialize a member variable (type.6).</DESCRIPTION>
    <FUNCTION>Vertex2D::{ctor}</FUNCTION>
    <DECORATED>??0Vertex2D@@QEAA@XZ</DECORATED>
    <FUNCLINE>6</FUNCLINE>
    <PATH></PATH>
  </DEFECT>
  <DEFECT>
    <SFA>
      <FILEPATH>c:\vsdev\classes\gameengines\insightengine\directx11renderingengine\graphics</FILEPATH>
      <FILENAME>vertex.h</FILENAME>
      <LINE>6</LINE>
      <COLUMN>1</COLUMN>
    </SFA>
    <DEFECTCODE>26495</DEFECTCODE>
    <DESCRIPTION>Variable 'Vertex2D::texCoord' is uninitialized. Always initialize a member variable (type.6).</DESCRIPTION>
    <FUNCTION>Vertex2D::{ctor}</FUNCTION>
    <DECORATED>??0Vertex2D@@QEAA@XZ</DECORATED>
    <FUNCLINE>6</FUNCLINE>
    <PATH></PATH>
  </DEFECT>
  <DEFECT>
    <SFA>
      <FILEPATH>c:\vsdev\classes\gameengines\insightengine\directx11renderingengine\graphics</FILEPATH>
      <FILENAME>vertex.h</FILENAME>
      <LINE>7</LINE>
      <COLUMN>1</COLUMN>
    </SFA>
    <DEFECTCODE>26495</DEFECTCODE>
    <DESCRIPTION>Variable 'Vertex2D::normal' is uninitialized. Always initialize a member variable (type.6).</DESCRIPTION>
    <FUNCTION>Vertex2D::{ctor}</FUNCTION>
    <DECORATED>??0Vertex2D@@QEAA@MMMMM@Z</DECORATED>
    <FUNCLINE>7</FUNCLINE>
    <PATH></PATH>
  </DEFECT>
  <DEFECT>
    <SFA>
      <FILEPATH>c:\vsdev\classes\gameengines\insightengine\directx11renderingengine\graphics</FILEPATH>
      <FILENAME>vertex.h</FILENAME>
      <LINE>17</LINE>
      <COLUMN>1</COLUMN>
    </SFA>
    <DEFECTCODE>26495</DEFECTCODE>
    <DESCRIPTION>Variable 'Vertex3D::texCoord' is uninitialized. Always initialize a member variable (type.6).</DESCRIPTION>
    <FUNCTION>Vertex3D::{ctor}</FUNCTION>
    <DECORATED>??0Vertex3D@@QEAA@XZ</DECORATED>
    <FUNCLINE>17</FUNCLINE>
    <PATH></PATH>
  </DEFECT>
  <DEFECT>
    <SFA>
      <FILEPATH>c:\vsdev\classes\gameengines\insightengine\directx11renderingengine\graphics</FILEPATH>
      <FILENAME>vertex.h</FILENAME>
      <LINE>17</LINE>
      <COLUMN>1</COLUMN>
    </SFA>
    <DEFECTCODE>26495</DEFECTCODE>
    <DESCRIPTION>Variable 'Vertex3D::pos' is uninitialized. Always initialize a member variable (type.6).</DESCRIPTION>
    <FUNCTION>Vertex3D::{ctor}</FUNCTION>
    <DECORATED>??0Vertex3D@@QEAA@XZ</DECORATED>
    <FUNCLINE>17</FUNCLINE>
    <PATH></PATH>
  </DEFECT>
  <DEFECT>
    <SFA>
      <FILEPATH>c:\vsdev\classes\gameengines\insightengine\directx11renderingengine\graphics</FILEPATH>
      <FILENAME>vertex.h</FILENAME>
      <LINE>17</LINE>
      <COLUMN>1</COLUMN>
    </SFA>
    <DEFECTCODE>26495</DEFECTCODE>
    <DESCRIPTION>Variable 'Vertex3D::normal' is uninitialized. Always initialize a member variable (type.6).</DESCRIPTION>
    <FUNCTION>Vertex3D::{ctor}</FUNCTION>
    <DECORATED>??0Vertex3D@@QEAA@XZ</DECORATED>
    <FUNCLINE>17</FUNCLINE>
    <PATH></PATH>
  </DEFECT>
  <DEFECT>
    <SFA>
      <FILEPATH>c:\vsdev\classes\gameengines\insightengine\directx11renderingengine\includes\assimp</FILEPATH>
      <FILENAME>mesh.h</FILENAME>
      <LINE>152</LINE>
      <COLUMN>4</COLUMN>
    </SFA>
    <DEFECTCODE>26495</DEFECTCODE>
    <DESCRIPTION>Variable 'aiFace::mNumIndices' is uninitialized. Always initialize a member variable (type.6).</DESCRIPTION>
    <FUNCTION>aiFace::{ctor}</FUNCTION>
    <DECORATED>??0aiFace@@QEAA@AEBU0@@Z</DECORATED>
    <FUNCLINE>152</FUNCLINE>
    <PATH></PATH>
  </DEFECT>
  <DEFECT>
    <SFA>
      <FILEPATH>c:\vsdev\classes\gameengines\insightengine\directx11renderingengine\includes\assimp</FILEPATH>
      <FILENAME>mesh.h</FILENAME>
      <LINE>284</LINE>
      <COLUMN>4</COLUMN>
    </SFA>
    <DEFECTCODE>26495</DEFECTCODE>
    <DESCRIPTION>Variable 'aiBone::mWeights' is uninitialized. Always initialize a member variable (type.6).</DESCRIPTION>
    <FUNCTION>aiBone::{ctor}</FUNCTION>
    <DECORATED>??0aiBone@@QEAA@AEBU0@@Z</DECORATED>
    <FUNCLINE>284</FUNCLINE>
    <PATH></PATH>
  </DEFECT>
  <DEFECT>
    <SFA>
      <FILEPATH>c:\vsdev\classes\gameengines\insightengine\directx11renderingengine\includes\assimp</FILEPATH>
      <FILENAME>mesh.h</FILENAME>
      <LINE>450</LINE>
      <COLUMN>4</COLUMN>
    </SFA>
    <DEFECTCODE>26495</DEFECTCODE>
    <DESCRIPTION>Variable 'aiAnimMesh::mColors' is uninitialized. Always initialize a member variable (type.6).</DESCRIPTION>
    <FUNCTION>aiAnimMesh::{ctor}</FUNCTION>
    <DECORATED>??0aiAnimMesh@@QEAA@XZ</DECORATED>
    <FUNCLINE>450</FUNCLINE>
    <PATH></PATH>
  </DEFECT>
  <DEFECT>
    <SFA>
      <FILEPATH>c:\vsdev\classes\gameengines\insightengine\directx11renderingengine\includes\assimp</FILEPATH>
      <FILENAME>mesh.h</FILENAME>
      <LINE>450</LINE>
      <COLUMN>4</COLUMN>
    </SFA>
    <DEFECTCODE>26495</DEFECTCODE>
    <DESCRIPTION>Variable 'aiAnimMesh::mTextureCoords' is uninitialized. Always initialize a member variable (type.6).</DESCRIPTION>
    <FUNCTION>aiAnimMesh::{ctor}</FUNCTION>
    <DECORATED>??0aiAnimMesh@@QEAA@XZ</DECORATED>
    <FUNCLINE>450</FUNCLINE>
    <PATH></PATH>
  </DEFECT>
  <DEFECT>
    <SFA>
      <FILEPATH>c:\vsdev\classes\gameengines\insightengine\directx11renderingengine\includes\assimp</FILEPATH>
      <FILENAME>mesh.h</FILENAME>
      <LINE>709</LINE>
      <COLUMN>4</COLUMN>
    </SFA>
    <DEFECTCODE>26495</DEFECTCODE>
    <DESCRIPTION>Variable 'aiMesh::mTextureCoords' is uninitialized. Always initialize a member variable (type.6).</DESCRIPTION>
    <FUNCTION>aiMesh::{ctor}</FUNCTION>
    <DECORATED>??0aiMesh@@QEAA@XZ</DECORATED>
    <FUNCLINE>709</FUNCLINE>
    <PATH></PATH>
  </DEFECT>
  <DEFECT>
    <SFA>
      <FILEPATH>c:\vsdev\classes\gameengines\insightengine\directx11renderingengine\includes\assimp</FILEPATH>
      <FILENAME>mesh.h</FILENAME>
      <LINE>709</LINE>
      <COLUMN>4</COLUMN>
    </SFA>
    <DEFECTCODE>26495</DEFECTCODE>
    <DESCRIPTION>Variable 'aiMesh::mNumUVComponents' is uninitialized. Always initialize a member variable (type.6).</DESCRIPTION>
    <FUNCTION>aiMesh::{ctor}</FUNCTION>
    <DECORATED>??0aiMesh@@QEAA@XZ</DECORATED>
    <FUNCLINE>709</FUNCLINE>
    <PATH></PATH>
  </DEFECT>
  <DEFECT>
    <SFA>
      <FILEPATH>c:\vsdev\classes\gameengines\insightengine\directx11renderingengine\includes\assimp</FILEPATH>
      <FILENAME>mesh.h</FILENAME>
      <LINE>709</LINE>
      <COLUMN>4</COLUMN>
    </SFA>
    <DEFECTCODE>26495</DEFECTCODE>
    <DESCRIPTION>Variable 'aiMesh::mColors' is uninitialized. Always initialize a member variable (type.6).</DESCRIPTION>
    <FUNCTION>aiMesh::{ctor}</FUNCTION>
    <DECORATED>??0aiMesh@@QEAA@XZ</DECORATED>
    <FUNCLINE>709</FUNCLINE>
    <PATH></PATH>
  </DEFECT>
  <DEFECT>
    <SFA>
      <FILEPATH>c:\vsdev\classes\gameengines\insightengine\directx11renderingengine\components</FILEPATH>
      <FILENAME>aabb.h</FILENAME>
      <LINE>8</LINE>
      <COLUMN>1</COLUMN>
    </SFA>
    <DEFECTCODE>26495</DEFECTCODE>
    <DESCRIPTION>Variable 'AABB::m_position' is uninitialized. Always initialize a member variable (type.6).</DESCRIPTION>
    <FUNCTION>AABB::{ctor}</FUNCTION>
    <DECORATED>??0AABB@@QEAA@M@Z</DECORATED>
    <FUNCLINE>8</FUNCLINE>
    <PATH></PATH>
  </DEFECT>
</DEFECTS>